Metadata-Version: 2.1
Name: qfree
Version: 0.1.0
Summary: Quantitative Trading Toolkit
Author: leesp
Author-email: leesp8@yeah.net
Classifier: Programming Language :: Python :: 3
Classifier: Operating System :: Unix
Classifier: Operating System :: Microsoft :: Windows
License-File: LICENSE
